djautotask/__init__.py
djautotask/admin.py
djautotask/api.py
djautotask/apps.py
djautotask/models.py
djautotask/sync.py
djautotask/urls.py
djautotask/utils.py
djautotask/views.py
djautotask/__pycache__/__init__.cpython-38.pyc
djautotask/__pycache__/api.cpython-38.pyc
djautotask/__pycache__/apps.cpython-38.pyc
djautotask/__pycache__/models.cpython-38.pyc
djautotask/__pycache__/sync.cpython-38.pyc
djautotask/__pycache__/urls.cpython-38.pyc
djautotask/__pycache__/utils.cpython-38.pyc
djautotask/__pycache__/views.cpython-38.pyc
djautotask/management/__init__.py
djautotask/management/__pycache__/__init__.cpython-38.pyc
djautotask/management/commands/atsync.py
djautotask/management/commands/clearoldsyncjobs.py
djautotask/management/commands/list_users.py
djautotask/management/commands/__pycache__/atsync.cpython-38.pyc
djautotask/migrations/0001_initial.py
djautotask/migrations/0002_ticket_ticket_number.py
djautotask/migrations/0003_auto_20190913_0941.py
djautotask/migrations/0004_auto_20190913_1425.py
djautotask/migrations/0005_auto_20190916_1549.py
djautotask/migrations/0005_remove_ticketstatus_value.py
djautotask/migrations/0006_auto_20190916_1645.py
djautotask/migrations/0006_merge_20190920_1450.py
djautotask/migrations/0007_auto_20190917_1009.py
djautotask/migrations/0008_auto_20190917_1454.py
djautotask/migrations/0008_merge_20190920_1644.py
djautotask/migrations/0009_auto_20190918_1525.py
djautotask/migrations/0009_auto_20190920_1648.py
djautotask/migrations/0010_auto_20190923_0930.py
djautotask/migrations/0010_merge_20190923_1155.py
djautotask/migrations/0011_auto_20190923_1157.py
djautotask/migrations/0012_merge_20190923_1439.py
djautotask/migrations/0013_auto_20190923_1439.py
djautotask/migrations/0014_auto_20190930_1548.py
djautotask/migrations/0015_auto_20191001_0847.py
djautotask/migrations/0016_auto_20191021_0958.py
djautotask/migrations/0017_auto_20191021_1028.py
djautotask/migrations/0018_auto_20191029_1621.py
django_autotask-1.7.6.dist-info/LICENSE
django_autotask-1.7.6.dist-info/METADATA
django_autotask-1.7.6.dist-info/WHEEL
django_autotask-1.7.6.dist-info/top_level.txt
django_autotask-1.7.6.dist-info/RECORD
