Metadata-Version: 2.1
Name: django-autotask
Version: 1.7.6
Summary: Django app for working with Autotask. Defines models (tickets, members, companies, etc.) and callbacks.
Home-page: https://github.com/KerkhoffTechnologies/django-autotask
Author: Kerkhoff Technologies Inc.
Author-email: matt@kerkhofftech.ca
License: MIT
Keywords: django autotask rest api python
Classifier: Environment :: Web Environment
Classifier: Framework :: Django
Classifier: Intended Audience :: Developers
Classifier: License :: OSI Approved :: MIT License
Classifier: Operating System :: OS Independent
Classifier: Programming Language :: Python
Classifier: Programming Language :: Python :: 3
Classifier: Topic :: Internet :: WWW/HTTP
Classifier: Topic :: Internet :: WWW/HTTP :: Dynamic Content
Classifier: Development Status :: 1 - Planning
License-File: LICENSE
Requires-Dist: requests
Requires-Dist: django
Requires-Dist: python-dateutil
Requires-Dist: django-model-utils
Requires-Dist: django-braces
Requires-Dist: django-extensions
Requires-Dist: retrying
